enforce_ascii/__init__.py
enforce_ascii/__main__.py
enforce_ascii/cli.py
enforce_ascii/utils.py
enforce_ascii-0.2.1.dist-info/entry_points.txt
enforce_ascii-0.2.1.dist-info/WHEEL
enforce_ascii-0.2.1.dist-info/METADATA
enforce_ascii-0.2.1.dist-info/RECORD
