Metadata-Version: 2.1
Name: enforce-ascii
Version: 0.2.1
Summary: A pre-commit hook, that enforces ASCII content.
Home-page: https://github.com/brutus/enforce-ascii/
License: GPL-3.0-or-later
Author: Brutus
Author-email: brutus.dmc@googlemail.com
Requires-Python: >=3.6.1
Classifier: Development Status :: 4 - Beta
Classifier: License :: OSI Approved :: GNU General Public License v3 or later (GPLv3+)
Classifier: Programming Language :: Python
Classifier: Programming Language :: Python :: 3
Classifier: Programming Language :: Python :: 3.7
Classifier: Programming Language :: Python :: 3.8
Classifier: Topic :: Software Development :: Libraries :: Python Modules
Provides-Extra: dev
Provides-Extra: doc
Provides-Extra: test
Requires-Dist: chardet (>=3.0.4,<4.0.0)
Project-URL: Repository, https://github.com/brutus/enforce-ascii/
